vimeo_utils/__init__.py
vimeo_utils/client.py
vimeo_utils/constants.py
vimeo_utils/exceptions.py
vimeo_utils/utils.py
vimeo_utils/mixins/__init__.py
vimeo_utils/mixins/embed_presets.py
vimeo_utils/mixins/projects.py
vimeo_utils/mixins/user.py
vimeo_utils/mixins/videos.py
python_vimeo_utils-0.1.0.dist-info/AUTHORS.md
python_vimeo_utils-0.1.0.dist-info/LICENSE
python_vimeo_utils-0.1.0.dist-info/METADATA
python_vimeo_utils-0.1.0.dist-info/WHEEL
python_vimeo_utils-0.1.0.dist-info/top_level.txt
python_vimeo_utils-0.1.0.dist-info/RECORD
