Metadata-Version: 2.1
Name: python-vimeo-utils
Version: 0.1.0
Summary: Wrapper functions around pyvimeo for common interactions with the Vimeo SDK.
Author-email: Tim Santor <tsantor@xstudios.com>
Project-URL: Repository, https://github.com/tsantor/python-vimeo-utils.git
Project-URL: Issues, https://github.com/tsantor/python-vimeo-utils/issues
Project-URL: Changelog, https://github.com/tsantor/python-vimeo-utils/blob/master/HISTORY.md
Classifier: Development Status :: 5 - Production/Stable
Classifier: Environment :: Console
Classifier: Intended Audience :: Developers
Classifier: Natural Language :: English
Classifier: Programming Language :: Python :: 3.8
Classifier: Programming Language :: Python :: 3.9
Classifier: Programming Language :: Python :: 3.10
Classifier: Programming Language :: Python :: 3.11
Classifier: Programming Language :: Python :: 3.12
Requires-Python: >=3.8
License-File: LICENSE
License-File: AUTHORS.md
Requires-Dist: pyvimeo >=1.1.2
Provides-Extra: dev
